aliyunsdkcdn/__init__.py
aliyunsdkcdn/endpoint.py
aliyunsdkcdn/request/__init__.py
aliyunsdkcdn/request/v20180510/AddCdnDomainRequest.py
aliyunsdkcdn/request/v20180510/AddFCTriggerRequest.py
aliyunsdkcdn/request/v20180510/BatchAddCdnDomainRequest.py
aliyunsdkcdn/request/v20180510/BatchDeleteCdnDomainConfigRequest.py
aliyunsdkcdn/request/v20180510/BatchSetCdnDomainConfigRequest.py
aliyunsdkcdn/request/v20180510/BatchSetCdnDomainServerCertificateRequest.py
aliyunsdkcdn/request/v20180510/BatchStartCdnDomainRequest.py
aliyunsdkcdn/request/v20180510/BatchStopCdnDomainRequest.py
aliyunsdkcdn/request/v20180510/BatchUpdateCdnDomainRequest.py
aliyunsdkcdn/request/v20180510/CreateCdnCertificateSigningRequestRequest.py
aliyunsdkcdn/request/v20180510/CreateCdnDeliverTaskRequest.py
aliyunsdkcdn/request/v20180510/CreateCdnSubTaskRequest.py
aliyunsdkcdn/request/v20180510/CreateRealTimeLogDeliveryRequest.py
aliyunsdkcdn/request/v20180510/CreateUsageDetailDataExportTaskRequest.py
aliyunsdkcdn/request/v20180510/CreateUserUsageDataExportTaskRequest.py
aliyunsdkcdn/request/v20180510/DeleteCdnDeliverTaskRequest.py
aliyunsdkcdn/request/v20180510/DeleteCdnDomainRequest.py
aliyunsdkcdn/request/v20180510/DeleteCdnSubTaskRequest.py
aliyunsdkcdn/request/v20180510/DeleteFCTriggerRequest.py
aliyunsdkcdn/request/v20180510/DeleteRealTimeLogLogstoreRequest.py
aliyunsdkcdn/request/v20180510/DeleteRealtimeLogDeliveryRequest.py
aliyunsdkcdn/request/v20180510/DeleteSpecificConfigRequest.py
aliyunsdkcdn/request/v20180510/DeleteSpecificStagingConfigRequest.py
aliyunsdkcdn/request/v20180510/DeleteUsageDetailDataExportTaskRequest.py
aliyunsdkcdn/request/v20180510/DeleteUserUsageDataExportTaskRequest.py
aliyunsdkcdn/request/v20180510/DescribeBlockedRegionsRequest.py
aliyunsdkcdn/request/v20180510/DescribeCdnCertificateDetailRequest.py
aliyunsdkcdn/request/v20180510/DescribeCdnCertificateListRequest.py
aliyunsdkcdn/request/v20180510/DescribeCdnDeletedDomainsRequest.py
aliyun_python_sdk_cdn-3.8.8.dist-info/LICENSE
aliyun_python_sdk_cdn-3.8.8.dist-info/METADATA
aliyun_python_sdk_cdn-3.8.8.dist-info/WHEEL
aliyun_python_sdk_cdn-3.8.8.dist-info/top_level.txt
aliyun_python_sdk_cdn-3.8.8.dist-info/RECORD
